.editorconfig
.env
.gitignore
LICENSE
MANIFEST.in
Pipfile
Pipfile.lock
README.md
azure-pipelines.yml
docker-compose.yml
setup.py
tox.ini
brewblox_plaato/__init__.py
brewblox_plaato/__main__.py
brewblox_plaato/broadcaster.py
brewblox_plaato.egg-info/PKG-INFO
brewblox_plaato.egg-info/SOURCES.txt
brewblox_plaato.egg-info/dependency_links.txt
brewblox_plaato.egg-info/requires.txt
brewblox_plaato.egg-info/top_level.txt
config/.gitkeep
docker/.gitignore
docker/localbuild.sh
docker/amd/Dockerfile
docker/arm/Dockerfile
test/__init__.py
test/conftest.py